totally_real_retriever/__init__.py
totally_real_retriever/retriever.py
totally_real_retriever-0.1.1.dist-info/METADATA
totally_real_retriever-0.1.1.dist-info/WHEEL
totally_real_retriever-0.1.1.dist-info/RECORD
